algorithms/__init__.py
algorithms/arrays/__init__.py
algorithms/arrays/delete_nth.py
algorithms/arrays/flatten.py
algorithms/arrays/garage.py
algorithms/arrays/josephus.py
algorithms/arrays/longest_non_repeat.py
algorithms/arrays/max_ones_index.py
algorithms/arrays/merge_intervals.py
algorithms/arrays/missing_ranges.py
algorithms/arrays/move_zeros.py
algorithms/arrays/plus_one.py
algorithms/arrays/rotate.py
algorithms/arrays/summarize_ranges.py
algorithms/arrays/three_sum.py
algorithms/arrays/two_sum.py
algorithms/backtrack/__init__.py
algorithms/backtrack/add_operators.py
algorithms/backtrack/anagram.py
algorithms/backtrack/array_sum_combinations.py
algorithms/backtrack/combination_sum.py
algorithms/backtrack/factor_combinations.py
algorithms/backtrack/find_words.py
algorithms/backtrack/generate_abbreviations.py
algorithms/backtrack/generate_parenthesis.py
algorithms/backtrack/letter_combination.py
algorithms/backtrack/palindrome_partitioning.py
algorithms/backtrack/pattern_match.py
algorithms/backtrack/permute.py
algorithms/backtrack/permute_unique.py
algorithms/backtrack/subsets.py
algorithms/backtrack/subsets_unique.py
algorithms/bit/__init__.py
algorithms/bit/add_bitwise_operator.py
algorithms/bit/bit_operation.py
algorithms/bit/bytes_int_conversion.py
algorithms/bit/count_flips_to_convert.py
algorithms/bit/count_ones.py
algorithms/bit/find_difference.py
algorithms/bit/find_missing_number.py
algorithms/bit/flip_bit_longest_sequence.py
algorithms/bit/has_alternative_bit.py
algorithms/bit/insert_bit.py
algorithms/bit/power_of_two.py
algorithms/bit/remove_bit.py
algorithms/bit/reverse_bits.py
algorithms/bit/single_number.py
algorithms/bit/single_number2.py
algorithms/bit/single_number3.py
algorithms/bit/subsets.py
algorithms/bit/swap_pair.py
algorithms/graph/Transitive_Closure_DFS.py
algorithms/graph/__init__.py
algorithms/graph/checkDiGraphStronglyConnected.py
algorithms/graph/clone_graph.py
algorithms-0.1.3.dist-info/METADATA
algorithms-0.1.3.dist-info/RECORD
algorithms-0.1.3.dist-info/WHEEL
algorithms-0.1.3.dist-info/top_level.txt
