Metadata-Version: 2.1
Name: algorithms
Version: 0.1.3
Summary: Pythonic Data Structures and Algorithms
Home-page: https://github.com/keon/algorithms
Author: Algorithms Team & Contributors
Author-email: kwk236@gmail.com
License: MIT
Platform: UNKNOWN
Classifier: Programming Language :: Python :: 3
Classifier: Programming Language :: Python :: 3.4
Classifier: Programming Language :: Python :: 3.5
Classifier: Programming Language :: Python :: 3.6
